vault_pki_agent/__init__.py
vault_pki_agent/auth.py
vault_pki_agent/main.py
vault_pki_agent/pki_provider.py
vault_pki_agent/watchers/__init__.py
vault_pki_agent/watchers/certificates.py
vault_pki_agent/watchers/crl.py
vault_pki_agent-0.4.3.dist-info/entry_points.txt
vault_pki_agent-0.4.3.dist-info/LICENSE
vault_pki_agent-0.4.3.dist-info/WHEEL
vault_pki_agent-0.4.3.dist-info/METADATA
vault_pki_agent-0.4.3.dist-info/RECORD
