Metadata-Version: 2.1
Name: vault-pki-agent
Version: 0.4.3
Summary: Tool for auto-renewal certificates and CRL from Vault PKI.
License: MIT
Author: Anatoly Gusev
Author-email: a.gusev@sparklingtide.com
Requires-Python: >=3.8.10,<4.0.0
Classifier: License :: OSI Approved :: MIT License
Classifier: Programming Language :: Python :: 3
Classifier: Programming Language :: Python :: 3.9
Requires-Dist: cryptography (>=36.0.2,<37.0.0)
Requires-Dist: funcy (>=1.17,<2.0)
Requires-Dist: hvac (>=0.11.2,<0.12.0)
Requires-Dist: requests (>=2.27.1,<3.0.0)
